Metadata-Version: 1.2
Name: pykrakenapi
Version: 0.1.2
Summary: A Python implementation of the Kraken API.
Home-page: https://github.com/dominiktraxl/pykrakenapi/
Author: Dominik Traxl
Author-email: dominik.traxl@posteo.org
License: GNU GPL
Download-URL: https://github.com/dominiktraxl/pykrakenapi/tarball/v0.1.2
Platform: UNKNOWN
Classifier: License :: OSI Approved :: BSD License
Classifier: Operating System :: OS Independent
Classifier: Programming Language :: Python :: 3
Classifier: Programming Language :: Python :: 3.4
Classifier: Programming Language :: Python :: 3.5
Classifier: Programming Language :: Python :: 3.6
Classifier: Topic :: Software Development :: Libraries :: Python Modules
Requires-Python: >=3
